agentfactory_mcp_server/__init__.py
agentfactory_mcp_server/catalog.py
agentfactory_mcp_server/cleanup.py
agentfactory_mcp_server/database.py
agentfactory_mcp_server/middleware.py
agentfactory_mcp_server/runner.py
agentfactory_mcp_server/schemas.py
agentfactory_mcp_server-0.1.0.dist-info/METADATA
agentfactory_mcp_server-0.1.0.dist-info/WHEEL
agentfactory_mcp_server-0.1.0.dist-info/entry_points.txt
agentfactory_mcp_server-0.1.0.dist-info/RECORD
