Metadata-Version: 2.4
Name: agentfactory-mcp-server
Version: 0.1.0
Summary: Agent Factory MCP Server
Author: ACME Inc.
License: MIT
Requires-Python: >=3.12
Requires-Dist: docker>=7.0.0
Requires-Dist: fastapi
Requires-Dist: httpx>=0.28.1
Requires-Dist: mcp[cli]
Requires-Dist: pydantic-ai>=0.1.3
Requires-Dist: pydantic<3,>=2
Requires-Dist: pytest-asyncio>=0.26.0
Requires-Dist: sqlalchemy>=2.0.40
Requires-Dist: sqlite-utils
Requires-Dist: sqlmodel>=0.0.24
Requires-Dist: testcontainers>=4.10.0
Requires-Dist: uvicorn[standard]
Provides-Extra: dev
Requires-Dist: black; extra == 'dev'
Requires-Dist: flake8; extra == 'dev'
Requires-Dist: httpx; extra == 'dev'
Requires-Dist: isort; extra == 'dev'
Requires-Dist: mypy; extra == 'dev'
Requires-Dist: pre-commit; extra == 'dev'
Requires-Dist: pytest; extra == 'dev'
Requires-Dist: pytest-asyncio; extra == 'dev'
Requires-Dist: testcontainers>=3.7.1; extra == 'dev'
